[
    {
        "band": "Robert Glasper Featuring Yebba",
        "venue": "Blue Note NYC",
        "date": "1",
        "time": "6:00 PMSummerStage",
        "link": "https://www.bluenotejazz.com/nyc/shows/?calendar_view",
        "category": "Music",
        "genre": "Jazz"
    },
    {
        "band": "Dumpstaphunk",
        "venue": "Blue Note NYC",
        "date": "2",
        "time": "8:00 PM & 10:30 PMBlue Note Jazz Club",
        "link": "https://www.bluenotejazz.com/nyc/shows/?calendar_view",
        "category": "Music",
        "genre": "Jazz"
    },
    {
        "band": "Karl Denson's Tiny Universe featuring Weedie Braimah",
        "venue": "Blue Note NYC",
        "date": "3",
        "time": "8:00 PM & 10:30 PMBlue Note Jazz Club",
        "link": "https://www.bluenotejazz.com/nyc/shows/?calendar_view",
        "category": "Music",
        "genre": "Jazz"
    },
    {
        "band": "The World Famous Harlem Gospel Choir",
        "venue": "Blue Note NYC",
        "date": "4",
        "time": "1:30 PMBlue Note Jazz Club",
        "link": "https://www.bluenotejazz.com/nyc/shows/?calendar_view",
        "category": "Music",
        "genre": "Jazz"
    },
    {
        "band": "Ghost Note",
        "venue": "Blue Note NYC",
        "date": "5",
        "time": "8:00 PM & 10:30 PMBlue Note Jazz Club",
        "link": "https://www.bluenotejazz.com/nyc/shows/?calendar_view",
        "category": "Music",
        "genre": "Jazz"
    },
    {
        "band": "Ghost Note",
        "venue": "Blue Note NYC",
        "date": "6",
        "time": "8:00 PM & 10:30 PMBlue Note Jazz Club",
        "link": "https://www.bluenotejazz.com/nyc/shows/?calendar_view",
        "category": "Music",
        "genre": "Jazz"
    },
    {
        "band": "Ghost Note",
        "venue": "Blue Note NYC",
        "date": "7",
        "time": "8:00 PM & 10:30 PMBlue Note Jazz Club",
        "link": "https://www.bluenotejazz.com/nyc/shows/?calendar_view",
        "category": "Music",
        "genre": "Jazz"
    },
    {
        "band": "NEA Jazz Master Gary Bartz",
        "venue": "Blue Note NYC",
        "date": "8",
        "time": "8:00 PM & 10:30 PMBlue Note Jazz Club",
        "link": "https://www.bluenotejazz.com/nyc/shows/?calendar_view",
        "category": "Music",
        "genre": "Jazz"
    },
    {
        "band": "NEA Jazz Master Gary Bartz",
        "venue": "Blue Note NYC",
        "date": "9",
        "time": "8:00 PM & 10:30 PMBlue Note Jazz Club",
        "link": "https://www.bluenotejazz.com/nyc/shows/?calendar_view",
        "category": "Music",
        "genre": "Jazz"
    },
    {
        "band": "The Dan Pugach Nonet with Grammy Award-Winner Nicole Zuraitis",
        "venue": "Blue Note NYC",
        "date": "10",
        "time": "1:00 PMBlue Note Jazz Club",
        "link": "https://www.bluenotejazz.com/nyc/shows/?calendar_view",
        "category": "Music",
        "genre": "Jazz"
    },
    {
        "band": "The World Famous Harlem Gospel Choir",
        "venue": "Blue Note NYC",
        "date": "11",
        "time": "1:30 PMBlue Note Jazz Club",
        "link": "https://www.bluenotejazz.com/nyc/shows/?calendar_view",
        "category": "Music",
        "genre": "Jazz"
    },
    {
        "band": "PLUMB - David Murray/Questlove/Ray Angry",
        "venue": "Blue Note NYC",
        "date": "12",
        "time": "8:00 PM & 10:30 PMBlue Note Jazz Club",
        "link": "https://www.bluenotejazz.com/nyc/shows/?calendar_view",
        "category": "Music",
        "genre": "Jazz"
    },
    {
        "band": "PLUMB - David Murray/Questlove/Ray Angry",
        "venue": "Blue Note NYC",
        "date": "13",
        "time": "8:00 PM & 10:30 PMBlue Note Jazz Club",
        "link": "https://www.bluenotejazz.com/nyc/shows/?calendar_view",
        "category": "Music",
        "genre": "Jazz"
    },
    {
        "band": "PLUMB - David Murray/Questlove/Ray Angry",
        "venue": "Blue Note NYC",
        "date": "14",
        "time": "8:00 PM & 10:30 PMBlue Note Jazz Club",
        "link": "https://www.bluenotejazz.com/nyc/shows/?calendar_view",
        "category": "Music",
        "genre": "Jazz"
    },
    {
        "band": "The Dirty Dozen Brass Band",
        "venue": "Blue Note NYC",
        "date": "15",
        "time": "8:00 PM & 10:30 PMBlue Note Jazz Club",
        "link": "https://www.bluenotejazz.com/nyc/shows/?calendar_view",
        "category": "Music",
        "genre": "Jazz"
    },
    {
        "band": "The Dirty Dozen Brass Band",
        "venue": "Blue Note NYC",
        "date": "16",
        "time": "8:00 PM & 10:30 PMBlue Note Jazz Club",
        "link": "https://www.bluenotejazz.com/nyc/shows/?calendar_view",
        "category": "Music",
        "genre": "Jazz"
    },
    {
        "band": "Strictly Sinatra - A Tribute To Frank Sinatra Starring Michael Dutra & His 9-Pc. Big Band Ensemble",
        "venue": "Blue Note NYC",
        "date": "17",
        "time": "1:30 PMBlue Note Jazz Club",
        "link": "https://www.bluenotejazz.com/nyc/shows/?calendar_view",
        "category": "Music",
        "genre": "Jazz"
    },
    {
        "band": "The World Famous Harlem Gospel Choir",
        "venue": "Blue Note NYC",
        "date": "18",
        "time": "1:30 PMBlue Note Jazz Club",
        "link": "https://www.bluenotejazz.com/nyc/shows/?calendar_view",
        "category": "Music",
        "genre": "Jazz"
    },
    {
        "band": "Mick Jenkins performing - 10th anniversary of The Water[s]",
        "venue": "Blue Note NYC",
        "date": "19",
        "time": "8:00 PM & 10:30 PMBlue Note Jazz Club",
        "link": "https://www.bluenotejazz.com/nyc/shows/?calendar_view",
        "category": "Music",
        "genre": "Jazz"
    },
    {
        "band": "Mick Jenkins performing - 10th anniversary of The Water[s]",
        "venue": "Blue Note NYC",
        "date": "20",
        "time": "8:00 PM & 10:30 PMBlue Note Jazz Club",
        "link": "https://www.bluenotejazz.com/nyc/shows/?calendar_view",
        "category": "Music",
        "genre": "Jazz"
    },
    {
        "band": "Arturo Sandoval",
        "venue": "Blue Note NYC",
        "date": "21",
        "time": "8:00 PM & 10:30 PMBlue Note Jazz Club",
        "link": "https://www.bluenotejazz.com/nyc/shows/?calendar_view",
        "category": "Music",
        "genre": "Jazz"
    },
    {
        "band": "Arturo Sandoval",
        "venue": "Blue Note NYC",
        "date": "22",
        "time": "8:00 PM & 10:30 PMBlue Note Jazz Club",
        "link": "https://www.bluenotejazz.com/nyc/shows/?calendar_view",
        "category": "Music",
        "genre": "Jazz"
    },
    {
        "band": "Arturo Sandoval",
        "venue": "Blue Note NYC",
        "date": "23",
        "time": "8:00 PM & 10:30 PMBlue Note Jazz Club",
        "link": "https://www.bluenotejazz.com/nyc/shows/?calendar_view",
        "category": "Music",
        "genre": "Jazz"
    },
    {
        "band": "Milo Z \"NYC's Finest & Funkiest\"",
        "venue": "Blue Note NYC",
        "date": "24",
        "time": "1:00 PMBlue Note Jazz Club",
        "link": "https://www.bluenotejazz.com/nyc/shows/?calendar_view",
        "category": "Music",
        "genre": "Jazz"
    },
    {
        "band": "The World Famous Harlem Gospel Choir",
        "venue": "Blue Note NYC",
        "date": "25",
        "time": "1:30 PMBlue Note Jazz Club",
        "link": "https://www.bluenotejazz.com/nyc/shows/?calendar_view",
        "category": "Music",
        "genre": "Jazz"
    },
    {
        "band": "Ali Sethi",
        "venue": "Blue Note NYC",
        "date": "26",
        "time": "8:00 PM & 10:30 PMBlue Note Jazz Club",
        "link": "https://www.bluenotejazz.com/nyc/shows/?calendar_view",
        "category": "Music",
        "genre": "Jazz"
    },
    {
        "band": "Dizzy Gillespie All-Star Big Band",
        "venue": "Blue Note NYC",
        "date": "27",
        "time": "8:00 PM & 10:30 PMBlue Note Jazz Club",
        "link": "https://www.bluenotejazz.com/nyc/shows/?calendar_view",
        "category": "Music",
        "genre": "Jazz"
    },
    {
        "band": "Dizzy Gillespie All-Star Big Band",
        "venue": "Blue Note NYC",
        "date": "28",
        "time": "8:00 PM & 10:30 PMBlue Note Jazz Club",
        "link": "https://www.bluenotejazz.com/nyc/shows/?calendar_view",
        "category": "Music",
        "genre": "Jazz"
    },
    {
        "band": "Dizzy Gillespie All-Star Big Band",
        "venue": "Blue Note NYC",
        "date": "29",
        "time": "8:00 PM & 10:30 PMBlue Note Jazz Club",
        "link": "https://www.bluenotejazz.com/nyc/shows/?calendar_view",
        "category": "Music",
        "genre": "Jazz"
    },
    {
        "band": "Blue Note Jazz Festival Presents: The Black Radio Experience",
        "venue": "Blue Note NYC",
        "date": "30",
        "time": "12:00 PMThe Meritage Resort & Spa",
        "link": "https://www.bluenotejazz.com/nyc/shows/?calendar_view",
        "category": "Music",
        "genre": "Jazz"
    },
    {
        "band": "Blue Note Jazz Festival Presents: The Black Radio Experience",
        "venue": "Blue Note NYC",
        "date": "31",
        "time": "12:00 PMThe Meritage Resort & Spa",
        "link": "https://www.bluenotejazz.com/nyc/shows/?calendar_view",
        "category": "Music",
        "genre": "Jazz"
    },
    {
        "band": "No band information",
        "venue": "Blue Note NYC",
        "date": "No date info",
        "time": "No showtime info",
        "link": "https://www.bluenotejazz.com/nyc/shows/?calendar_view",
        "category": "Music",
        "genre": "Jazz"
    },
    {
        "band": "No band information",
        "venue": "Blue Note NYC",
        "date": "No date info",
        "time": "No showtime info",
        "link": "https://www.bluenotejazz.com/nyc/shows/?calendar_view",
        "category": "Music",
        "genre": "Jazz"
    },
    {
        "band": "JOE LOVANO & DAVE DOUGLAS QUINTET",
        "venue": "Village Vanguard",
        "date": "Sound Prints",
        "link": "https://villagevanguard.com/"
    },
    {
        "band": "VANGUARD JAZZ ORCHESTRA",
        "venue": "Village Vanguard",
        "date": "Every Monday Night",
        "link": "https://villagevanguard.com/"
    },
    {
        "band": "BILL CHARLAP TRIO",
        "venue": "Village Vanguard",
        "date": "Sep 3-8 & 10-15",
        "link": "https://villagevanguard.com/"
    },
    {
        "band": "Miguel Zenon Quartet",
        "venue": "Village Vanguard",
        "date": "September 17 - September 22",
        "link": "https://villagevanguard.com/"
    },
    {
        "band": "Mark Guiliana",
        "venue": "Village Vanguard",
        "date": "September 24 - September 29",
        "link": "https://villagevanguard.com/"
    },
    {
        "band": "COMING SOON!",
        "venue": "Village Vanguard",
        "date": "No band information",
        "link": "https://villagevanguard.com/"
    }
]